{
  "keyword": "Gravity Weighted Blanket",
  "max_results": 10,
  "timestamp": "2026-01-17T13:40:58.002930",
  "results": [
    {
      "title": "gravity blankets Gravity Weighted Blanket Single",
      "price": 94.99,
      "currency": "USD",
      "url": "https://www.google.com/search?ibp=oshop&q=Gravity Weighted Blanket&prds=catalogid:4014217978735396892,headlineOfferDocid:10121977849290533464,imageDocid:5727144371625396618,rds:PC_17290945732627407788|PROD_PC_17290945732627407788,gpcid:17290945732627407788,mid:576462807137070769,pvt:hg&hl=en&gl=us&udm=28",
      "image": "https://encrypted-tbn2.gstatic.com/shopping?q=tbn:ANd9GcRSh7fD6V2JoB5H9SW0rdGJ9PZcQROpxLfYtFRFARkaX_0VP354rNryoZJLWTGFaVfDynelregan230mmhZ04b2gkilpFP6aMLb2l44IIRGheeQvPnwVzt4",
      "platform": "Google Shopping",
      "source": "Gravity",
      "rating": 4.2,
      "reviews": 1500
    },
    {
      "title": "SereneLife Gravity Weighted Blanket",
      "price": 87.99,
      "currency": "USD",
      "url": "https://www.google.com/search?ibp=oshop&q=Gravity Weighted Blanket&prds=catalogid:468452413259225412,headlineOfferDocid:11211303020039972759,imageDocid:12032754735541780374,gpcid:13791720054266505556,mid:576462855057685733,pvt:hg&hl=en&gl=us&udm=28",
      "image": "https://encrypted-tbn2.gstatic.com/shopping?q=tbn:ANd9GcTjWh5RrJ5zxulstIVP874qu8lJgpmMbSoEoczDnfvczHuAn4fdwFhqEKND-t5lKgcImL6tCwInswR2ujNnxfNaF6SPEPExQw",
      "platform": "Google Shopping",
      "source": "Target",
      "rating": "",
      "reviews": ""
    },
    {
      "title": "Gravity Blanket Rejuve Weighted Blanket Reviews ? REJUVE BAMBOO WEIGHTED BLANKET, 12lb 48\u201dx72\u201d, Gray, Great",
      "price": 42.0,
      "currency": "USD",
      "url": "https://www.google.com/search?ibp=oshop&q=Gravity Weighted Blanket&prds=productid:4453488771976129622,headlineOfferDocid:4453488771976129622,imageDocid:16943072119091548356,pvt:hg&hl=en&gl=us&udm=28",
      "image": "https://encrypted-tbn0.gstatic.com/shopping?q=tbn:ANd9GcRK1foh5qgauiERdv44_KTs8YS9cHZ4KGZK18vWE-ftF1SvLbKiVBHtZaNr2ZJRWRD59c_4Ids0A7QkOSzdfAH78Nn00zc-",
      "platform": "Google Shopping",
      "source": "Circle K NZ",
      "rating": "",
      "reviews": ""
    },
    {
      "title": "Pottery Barn Gravity Quilted Weighted Blanket",
      "price": 159.98,
      "currency": "USD",
      "url": "https://www.google.com/search?ibp=oshop&q=Gravity Weighted Blanket&prds=catalogid:5305854372497054964,headlineOfferDocid:17282618046633933083,imageDocid:11438524699899182307,gpcid:12436488660513270140,mid:576462728282203028,pvt:hg&hl=en&gl=us&udm=28",
      "image": "https://encrypted-tbn3.gstatic.com/shopping?q=tbn:ANd9GcTR7ZiigDLhmWOgEh-pxP8LhbtDUYorOcpZTUXKOOfNDbip3QGL-wQS-pDKaUzH1eD8N-kRvVFQj4ljrMg_ycWs655kaOAyrezwuDTVSC7GRTQzlFIUffLFvw",
      "platform": "Google Shopping",
      "source": "USC Bookstore",
      "rating": "",
      "reviews": ""
    },
    {
      "title": "The Company Store Gravity Weighted Blanket",
      "price": 124.99,
      "currency": "USD",
      "url": "https://www.google.com/search?ibp=oshop&q=Gravity Weighted Blanket&prds=catalogid:177640615193244226,headlineOfferDocid:1901499386802810425,imageDocid:1520325743070632276,rds:PC_17529293123340334109|PROD_PC_17529293123340334109,gpcid:17529293123340334109,mid:576462863034181834,pvt:hg&hl=en&gl=us&udm=28",
      "image": "https://encrypted-tbn0.gstatic.com/shopping?q=tbn:ANd9GcTuQuiFcuX6gmquRA9M_mhrYOaA3uidRoaiNPjwq9pHqd2GL-ubE5SCqM5Eeuo-urDHvWMa4E9LLf-XihNSyx7IlFVBTa39zsG8GRQ_mxp_b1vU6mOmyp2uuA",
      "platform": "Google Shopping",
      "source": "Gravity",
      "rating": 4.2,
      "reviews": 1400
    },
    {
      "title": "Gravity Blue Premium Weighted Blanket Micro Fleece Duvet Cover 48\" x 72\", 15lbs",
      "price": 50.0,
      "currency": "USD",
      "url": "https://www.google.com/search?ibp=oshop&q=Gravity Weighted Blanket&prds=productid:10963410278896638790,headlineOfferDocid:10963410278896638790,imageDocid:770513529475830672,pvt:hg&hl=en&gl=us&udm=28",
      "image": "https://serpapi.com/searches/696bd7b2bdfe49f0e78e8c44/images/108a4cb3198314a23f54c3581457106c698472ad07d4c8845704aaf26f6efd09.webp",
      "platform": "Google Shopping",
      "source": "eBay",
      "rating": "",
      "reviews": ""
    },
    {
      "title": "Gravity Chunky Knit Blanket",
      "price": 99.99,
      "currency": "USD",
      "url": "https://www.google.com/search?ibp=oshop&q=Gravity Weighted Blanket&prds=catalogid:4808655726295437984,headlineOfferDocid:16594989719544525178,imageDocid:13280543414630424808,rds:PC_11088641899308921129|PROD_PC_11088641899308921129,gpcid:11088641899308921129,mid:576462688082330476,pvt:hg&hl=en&gl=us&udm=28",
      "image": "https://encrypted-tbn0.gstatic.com/shopping?q=tbn:ANd9GcSgQIwpEkG-VWziwX3DvAHNFh6Lb9eJHpeGe8pc2DkH0PlKWM2mC9iiZr1cjXI3mQmNxklRPLuxW4nWtMG5e3HjK99vuizXVvfcZnx9RQa4zpG_J0zDD3Vy6A",
      "platform": "Google Shopping",
      "source": "Gravity",
      "rating": 3.6,
      "reviews": 59
    },
    {
      "title": "Gravity Blankets Gravity Cooling Weighted Blanket Single",
      "price": 142.49,
      "currency": "USD",
      "url": "https://www.google.com/search?ibp=oshop&q=Gravity Weighted Blanket&prds=catalogid:863035444101706362,headlineOfferDocid:15299747317241318169,imageDocid:8148453439741534247,rds:PC_18378773531186310870|PROD_PC_18378773531186310870,gpcid:18378773531186310870,mid:576462821501916582,pvt:hg&hl=en&gl=us&udm=28",
      "image": "https://encrypted-tbn3.gstatic.com/shopping?q=tbn:ANd9GcTIh9hZKUp7Pyc8ebUePtFodeDAUJQsTzvsD_-njnyKdFKPVhsTB7sPXzMRx9pv3nzh1b7L4YEFf-Xlr3Q6-dvHdBLFfYLMLa4IVhkWDN56KKyL6oZQODDB",
      "platform": "Google Shopping",
      "source": "eBay - usedshoesandmore",
      "rating": 4.0,
      "reviews": 1200
    },
    {
      "title": "Clearance gravity blanket purple New Arrivals 20 Best Weighted Blankets in 2022 Gravity Blanket Bearaby",
      "price": 52.0,
      "currency": "USD",
      "url": "https://www.google.com/search?ibp=oshop&q=Gravity Weighted Blanket&prds=productid:9746526588200877199,headlineOfferDocid:9746526588200877199,imageDocid:2308147857352954998,pvt:hg&hl=en&gl=us&udm=28",
      "image": "https://encrypted-tbn2.gstatic.com/shopping?q=tbn:ANd9GcQLAQZailWRzVmBaQ8mmyppWXwldHDA9VFBc36ifntKl-3bLNiC1Hq0Ou8MXQKfEDu5-TQYJnJgETYf0GBV42kSneEa9Gvv",
      "platform": "Google Shopping",
      "source": "timberlinegym.com",
      "rating": "",
      "reviews": ""
    },
    {
      "title": "Breeze Cooling Weighted Blanket",
      "price": 181.0,
      "currency": "USD",
      "url": "https://www.google.com/search?ibp=oshop&q=Gravity Weighted Blanket&prds=productid:7283956862459545171,headlineOfferDocid:7283956862459545171,imageDocid:17847254738585489488,pvt:hg&hl=en&gl=us&udm=28",
      "image": "https://encrypted-tbn0.gstatic.com/shopping?q=tbn:ANd9GcRguf3TbCGT72tsyn0GXPDOkMemjnUK0BHUUCrpuRmkDQtfcjKNvccCLcHe3dcl_8-d-JeeJd49ioKlI6GBIbUo9oCT-U35",
      "platform": "Google Shopping",
      "source": "Gravid Weighted Blankets",
      "rating": "",
      "reviews": ""
    },
    {
      "title": "Gravity Weighted Blanket",
      "price": 109.0,
      "currency": "USD",
      "url": "https://www.google.com/search?ibp=oshop&q=Gravity Weighted Blanket&prds=productid:5876878060569094695,headlineOfferDocid:5876878060569094695,imageDocid:10992791175422805643,pvt:hg&hl=en&gl=us&udm=28",
      "image": "https://encrypted-tbn3.gstatic.com/shopping?q=tbn:ANd9GcSxOA46zAEF9LKgF5mGJKCapYIIODXgKX1zHqCQ_yL9nomAYIBTJchPfi_hxsW8f63y2_iDQvbVNMjKhLnFsSOWdcGNN0H3IxFXUdq4VOBoGQQw-PvA7BbQ4A",
      "platform": "Google Shopping",
      "source": "Let's Truck",
      "rating": "",
      "reviews": ""
    },
    {
      "title": "Modernist by Gravity Weighted Blanket",
      "price": 89.99,
      "currency": "USD",
      "url": "https://www.google.com/search?ibp=oshop&q=Gravity Weighted Blanket&prds=catalogid:2018231907305050804,headlineOfferDocid:10474144107255724450,imageDocid:12358954188367222234,gpcid:10631298872051901199,mid:576462503051040401,pvt:hg&hl=en&gl=us&udm=28",
      "image": "https://encrypted-tbn2.gstatic.com/shopping?q=tbn:ANd9GcRr_OAcD4ICycpX3MKevhSjW0bqJrfNdC6HgMp7GMf_RYc7asZ9cYtsScXC4bvMfzlXDc8HdeMbTg93fQOgOJZ6Ljl-r8A33GTEV72m4aqSVQS2SpG5gprR",
      "platform": "Google Shopping",
      "source": "eBay - usedshoesandmore",
      "rating": "",
      "reviews": ""
    },
    {
      "title": "DreamZ Weighted Blanket Heavy Gravity Deep Relax 2.3KG Adult Kids Grey",
      "price": 20.99,
      "currency": "USD",
      "url": "https://www.google.com/search?ibp=oshop&q=Gravity Weighted Blanket&prds=productid:9054442668210160019,headlineOfferDocid:9054442668210160019,imageDocid:1869595088730863047,pvt:hg&hl=en&gl=us&udm=28",
      "image": "https://encrypted-tbn3.gstatic.com/shopping?q=tbn:ANd9GcQTunrXiUoeLLXrswsk5lEk7HKqDKMEBscikoDTGWpYeLiE8x2ok5KQN2hqhEeVVYktPrv6HuvnAUsOzCO9Pd2HoBj7aYwAsbSxs564UKs-3-dJrd0YetvjAQ",
      "platform": "Google Shopping",
      "source": "UPShop",
      "rating": "",
      "reviews": ""
    },
    {
      "title": "Cotton Gravity Weighted Soothing Blanket - Light gray / 91\u00d7122cm",
      "price": 85.0,
      "currency": "USD",
      "url": "https://www.google.com/search?ibp=oshop&q=Gravity Weighted Blanket&prds=productid:11040171633229820275,headlineOfferDocid:11040171633229820275,imageDocid:17765239334656660246,pvt:hg&hl=en&gl=us&udm=28",
      "image": "https://encrypted-tbn2.gstatic.com/shopping?q=tbn:ANd9GcRCx5AZZwuQ-_y1pWtqhjzGtZY5fRl22yPxYX27BqRvWKicfWp2X4dz47OrPEN8C2GcSp2jQTGp08vady8W32oqoZbigbszlZP1MKYyUq99BqBOmaG9S1sWOA",
      "platform": "Google Shopping",
      "source": "Sensory Therapy Place",
      "rating": "",
      "reviews": ""
    },
    {
      "title": "SensoryHarbor Gravity Blanket for Kids with Autism, ADHD, & Better Sleep",
      "price": 129.99,
      "currency": "USD",
      "url": "https://www.google.com/search?ibp=oshop&q=Gravity Weighted Blanket&prds=catalogid:9162835118490094321,headlineOfferDocid:6468876775284371869,imageDocid:4816050291684746491,gpcid:5458208350017999184,pvt:hg&hl=en&gl=us&udm=28",
      "image": "https://encrypted-tbn3.gstatic.com/shopping?q=tbn:ANd9GcR0i1r_QQ2c5EeRFapISerDB6MMQxZRXa6ygSLMR14lnplx9oX_Tj1UihKMaa1E_TFjB09LSjGcxkfiAinTnh3b5tM7ZQFgpSR1IZX6Lr0EXu4Effii2ZSPaA",
      "platform": "Google Shopping",
      "source": "SensoryHarbor",
      "rating": "",
      "reviews": ""
    },
    {
      "title": "pothos beauty Gravity Weighted Blanket Ombre Single",
      "price": 97.49,
      "currency": "USD",
      "url": "https://www.google.com/search?ibp=oshop&q=Gravity Weighted Blanket&prds=catalogid:17875021781963784317,headlineOfferDocid:10186620636696240019,imageDocid:6192538453561967650,rds:PC_12038796632235544146|PROD_PC_12038796632235544146,gpcid:12038796632235544146,mid:576462671848045326,pvt:hg&hl=en&gl=us&udm=28",
      "image": "https://encrypted-tbn2.gstatic.com/shopping?q=tbn:ANd9GcSuajz5Tn8_b49eDbsUwA671pXuo9S9_DqX86IjqsvWe6GjXLG6Mwp8PniMpwlmbW7wyYfyuMzMYFAtV9ymyBoV8xGSVt63BD-ZVF5woLkglJI1V9Q8D4tkJRY",
      "platform": "Google Shopping",
      "source": "eBay - usedshoesandmore",
      "rating": 4.3,
      "reviews": 47
    },
    {
      "title": "Weighted Gravity Blanket with Removable Blanket Swift Home",
      "price": 50.03,
      "currency": "USD",
      "url": "https://www.google.com/search?ibp=oshop&q=Gravity Weighted Blanket&prds=catalogid:9124297727792405424,headlineOfferDocid:6628379081567362371,imageDocid:12850108057050395669,rds:PC_8493966345662048850|PROD_PC_8493966345662048850,gpcid:8493966345662048850,mid:576462763394668990,pvt:hg&hl=en&gl=us&udm=28",
      "image": "https://encrypted-tbn1.gstatic.com/shopping?q=tbn:ANd9GcRiJBPEC1rPFsy2srppKPH6RzTzLuxyYYDME7R5MUPW3wl3xQmlmjin4ZpgbXZNgB-qz8Wm8OQ549RrLh637zNw6jjcIozqoXnod40fU6rrADJc7BaikQ2d",
      "platform": "Google Shopping",
      "source": "Wayfair",
      "rating": 4.4,
      "reviews": 268
    },
    {
      "title": "Zero Gravity NWT Gravity Original Weighted Blanket Navy - New Home",
      "price": 70.0,
      "currency": "USD",
      "url": "https://www.google.com/search?ibp=oshop&q=Gravity Weighted Blanket&prds=productid:6475509853627093774,headlineOfferDocid:6475509853627093774,imageDocid:4858307570091776723,pvt:hg&hl=en&gl=us&udm=28",
      "image": "https://encrypted-tbn3.gstatic.com/shopping?q=tbn:ANd9GcRKQBuMDLQGORlZCH4xnI7sixtRiJVCvHxk7HtUXsAJiZi9GuBzHkPf8PDmUuihR4Csq3r33KLokns5SwKq_ZnIytEVTeWK9wYFf0nMU3UT",
      "platform": "Google Shopping",
      "source": "Mercari",
      "rating": "",
      "reviews": ""
    },
    {
      "title": "Gravity Weighted Blanket Gray",
      "price": 100.0,
      "currency": "USD",
      "url": "https://www.google.com/search?ibp=oshop&q=Gravity Weighted Blanket&prds=productid:12637802153669011287,headlineOfferDocid:12637802153669011287,imageDocid:10921728809966879825,pvt:hg&hl=en&gl=us&udm=28",
      "image": "https://encrypted-tbn1.gstatic.com/shopping?q=tbn:ANd9GcTFy-B6qKki5NSRRWL039qDbWfzZTNddO_tlFZl7Jk0wKfg63R1NoFBUTLU4rIUJ95qpVxWuPHEv6bEQXXtR2dpPFeTpgC9_r_V48Fvf2FVha5LIxfAz8vh7FZR",
      "platform": "Google Shopping",
      "source": "coop & spree",
      "rating": "",
      "reviews": ""
    },
    {
      "title": "Gravity Weighted Blanket for Adults Blue 30lb King Size Glass Bead Fill",
      "price": 50.99,
      "currency": "USD",
      "url": "https://www.google.com/search?ibp=oshop&q=Gravity Weighted Blanket&prds=productid:9393953403808979151,headlineOfferDocid:9393953403808979151,imageDocid:10854179960224790982,pvt:hg&hl=en&gl=us&udm=28",
      "image": "https://encrypted-tbn2.gstatic.com/shopping?q=tbn:ANd9GcQLf9gF4QWO-5VwVYSyUnG2B29E5laKY0eeOc0-aJQOMQz8aUPGu719kWf2K6ZFkApvDplZzNh251SaxMAGM1oT7W-9aGMsMsuyu3J-5ffYYqbDRWvIqOPl",
      "platform": "Google Shopping",
      "source": "eBay",
      "rating": "",
      "reviews": ""
    },
    {
      "title": "Gravity blanket 25 Pounds",
      "price": 79.8,
      "currency": "USD",
      "url": "https://www.google.com/search?ibp=oshop&q=Gravity Weighted Blanket&prds=productid:17970486512544111321,headlineOfferDocid:17970486512544111321,imageDocid:2488837935836746510,pvt:hg&hl=en&gl=us&udm=28",
      "image": "https://encrypted-tbn2.gstatic.com/shopping?q=tbn:ANd9GcRKklxD914xAdELtSam_11FF8I69srN3o1kLBiGqEJLxZpUh4rQ8CnokTmvPDVfC3Fa26jp13H_B_BKykyhFU-prUaFhMGs",
      "platform": "Google Shopping",
      "source": "Mary Mahoney's",
      "rating": "",
      "reviews": ""
    },
    {
      "title": "Bell + Howell Weighted Blanket",
      "price": 49.99,
      "currency": "USD",
      "url": "https://www.google.com/search?ibp=oshop&q=Gravity Weighted Blanket&prds=catalogid:945696781670411287,headlineOfferDocid:13593560770550903031,imageDocid:6765481061887209281,rds:PC_4825854209631731363|PROD_PC_4825854209631731363,gpcid:4825854209631731363,mid:576462371782616083,pvt:hg&hl=en&gl=us&udm=28",
      "image": "https://encrypted-tbn1.gstatic.com/shopping?q=tbn:ANd9GcSHg66kKHulMzHATfP7ZudzlOYayxQuOWSRO9zKXcWI-1wFaEs6Ejswd4maBBNNM3fhjTBOBOry__A9A1REWKCdHJ9qmoSR",
      "platform": "Google Shopping",
      "source": "Walmart - Realco Direct",
      "rating": 4.0,
      "reviews": 307
    },
    {
      "title": "Gravity Weighted Blanket Gray Cotton Twin Modern | Double | 12lbs 15lbs 20lbs | Rectangular | Bedroom",
      "price": 31.58,
      "currency": "USD",
      "url": "https://www.google.com/search?ibp=oshop&q=Gravity Weighted Blanket&prds=productid:14751545733441881148,headlineOfferDocid:14751545733441881148,imageDocid:16262735575762870392,pvt:hg&hl=en&gl=us&udm=28",
      "image": "https://encrypted-tbn0.gstatic.com/shopping?q=tbn:ANd9GcT7Yk7C9V0llPdQvIrCt4SBbPqlI8L6b1hYTu_wOwG_3CkpZ0Hyu5dCiCvjurmTf4faHpt24hfO_kWBKV_Ib_hvxpje9MBHJAgSjoNdMsD9h3Bl_jhLw0NC",
      "platform": "Google Shopping",
      "source": "eBay - pro-equipment-supplier",
      "rating": "",
      "reviews": ""
    },
    {
      "title": "Zero Gravity Weighted Blanket - New Home | Color: Grey",
      "price": 48.0,
      "currency": "USD",
      "url": "https://www.google.com/search?ibp=oshop&q=Gravity Weighted Blanket&prds=productid:7886361090226925494,headlineOfferDocid:7886361090226925494,imageDocid:11930509970464888890,pvt:hg&hl=en&gl=us&udm=28",
      "image": "https://encrypted-tbn2.gstatic.com/shopping?q=tbn:ANd9GcT11jCkAqE_UVP9L-I-z80dYeQi4w5NH3WUoPRLBx8Vi3XVuLpoLTxfYplODkKZ_vPvaVIEpLDmkkjULAYTq3SHsV89LAyE86rBNKnbR21a",
      "platform": "Google Shopping",
      "source": "Mercari",
      "rating": "",
      "reviews": ""
    },
    {
      "title": "Bearaby Cotton Knitted Weighted Blanket",
      "price": 199.0,
      "currency": "USD",
      "url": "https://www.google.com/search?ibp=oshop&q=Gravity Weighted Blanket&prds=catalogid:14057766188363684711,headlineOfferDocid:11837465795192944392,imageDocid:17367362363939193742,rds:PC_212713938097413150|PROD_PC_212713938097413150,gpcid:212713938097413150,mid:576462503845758382,pvt:hg&hl=en&gl=us&udm=28",
      "image": "https://encrypted-tbn2.gstatic.com/shopping?q=tbn:ANd9GcRNkufxFCDc5Ikdj6hljkLWwHAzIpaat5NuuHU7bSMpN24epsEQRssNrzV-ORhxEVJWo7dAc95kVpijmGZPiegxuOmqnBFnSQmHDBq_-QTIpkhdSSIwtofx7Q",
      "platform": "Google Shopping",
      "source": "Bearaby",
      "rating": 4.3,
      "reviews": 2900
    },
    {
      "title": "Gravity Zippered Weighted Blanket",
      "price": 134.99,
      "currency": "USD",
      "url": "https://www.google.com/search?ibp=oshop&q=Gravity Weighted Blanket&prds=catalogid:10785376313979773749,headlineOfferDocid:13699202101266113816,imageDocid:8598109809771193153,rds:PC_8504561632881927093|PROD_PC_8504561632881927093,gpcid:8504561632881927093,pvt:hg&hl=en&gl=us&udm=28",
      "image": "https://encrypted-tbn1.gstatic.com/shopping?q=tbn:ANd9GcRT4mpM-sRbF-XQcDvnenQPpVM0FO3RIyL1Pd7yCBATHvTVgtuhIJFrMG_R0wayk9cVX-NSVvAPRKCn2GR_gS9IHBePEKANShJhzMD8HsgRJs7VuLV6PZ6_k8Y",
      "platform": "Google Shopping",
      "source": "eBay - usedshoesandmore",
      "rating": 4.7,
      "reviews": 156
    },
    {
      "title": "Weighted Blanket | Gravity Blanket | Blanket | Granjoy Blanket Grey / 150 x 200cm (6.5KG)",
      "price": 123.39,
      "currency": "USD",
      "url": "https://www.google.com/search?ibp=oshop&q=Gravity Weighted Blanket&prds=productid:17281284193898628636,headlineOfferDocid:17281284193898628636,imageDocid:2719599316642657769,rds:LO_17281284193898628636|PROD_LO_17281284193898628636,pvt:hg&hl=en&gl=us&udm=28",
      "image": "https://encrypted-tbn1.gstatic.com/shopping?q=tbn:ANd9GcR_U-RueQBWvo7uecMgHRa-8ovac9Dw4PEECUtkCs6m8PBxFNSN9MyUlyPGBk8jj349LoozcCn4t8gZjvgRgnMFn3UQxYmJ6nT2ytzB7Np0",
      "platform": "Google Shopping",
      "source": "Granjoy",
      "rating": 4.8,
      "reviews": 21
    },
    {
      "title": "Gravity Blanket Mr Price Weighted Blanket Reviews Pendleton Weighted Blanket Reviews Pendleton Glass Micro Beads",
      "price": 40.0,
      "currency": "USD",
      "url": "https://www.google.com/search?ibp=oshop&q=Gravity Weighted Blanket&prds=productid:5951087343683507305,headlineOfferDocid:5951087343683507305,imageDocid:17314790193152310843,pvt:hg&hl=en&gl=us&udm=28",
      "image": "https://encrypted-tbn3.gstatic.com/shopping?q=tbn:ANd9GcQeCKl0Qc3aqR5qHFPOb_FvDOlJIHS7NxZ7UP0abfO67AjYZDUez2XWqe1jTZaCO6fl1-9FDDPXvvd6rK38NUH2ouqoI81n",
      "platform": "Google Shopping",
      "source": "Laboratoire Bizeau",
      "rating": "",
      "reviews": ""
    },
    {
      "title": "Zero Gravity Weighted Blanket 15lbs! - New Home | Color: Grey",
      "price": 60.0,
      "currency": "USD",
      "url": "https://www.google.com/search?ibp=oshop&q=Gravity Weighted Blanket&prds=productid:181183647489504488,headlineOfferDocid:181183647489504488,imageDocid:2319052992490594125,pvt:hg&hl=en&gl=us&udm=28",
      "image": "https://encrypted-tbn1.gstatic.com/shopping?q=tbn:ANd9GcQa4I7PUWDy_w2XaiZEIVLHXrZ4kfJZCoHBRt2W1TSI54jVBKNxOjI3E2WuIW-5E0EGuhKYes0XPzdQBDOqy953_rE7wW9hgTtXrIsyMAjr",
      "platform": "Google Shopping",
      "source": "Mercari",
      "rating": "",
      "reviews": ""
    },
    {
      "title": "Ynm Weighted Blanket 15 lbs 48x72 Twin Size Premium Cotton & Glass Beads Gravity 2.0 Heavy Blanket Great Sleep Therapy for People",
      "price": 25.0,
      "currency": "USD",
      "url": "https://www.google.com/search?ibp=oshop&q=Gravity Weighted Blanket&prds=catalogid:8572998198083748501,headlineOfferDocid:15881669935409529380,imageDocid:3971999962514222424,rds:PC_2963423562797053584|PROD_PC_2963423562797053584,gpcid:2963423562797053584,mid:576462876415949582,pvt:hg&hl=en&gl=us&udm=28",
      "image": "https://encrypted-tbn0.gstatic.com/shopping?q=tbn:ANd9GcSHN1Y0HaMspf3k6wKqT8NNh2tiJOGNM8XG90nB7B4XEApTb00exROPeJskaYSRYpyqNpJE7T5UfRT4qLEGIejjmKeG0WUR9QeWavZjRR2_OMl5s1Vkft76",
      "platform": "Google Shopping",
      "source": "eBay",
      "rating": 4.0,
      "reviews": 5
    },
    {
      "title": "Gravity Chunky Knit Weighted Blanket (Single - 42 x 65 - 10lbs) in White",
      "price": 99.0,
      "currency": "USD",
      "url": "https://www.google.com/search?ibp=oshop&q=Gravity Weighted Blanket&prds=productid:11953122477568808860,headlineOfferDocid:11953122477568808860,imageDocid:15783493746179522407,pvt:hg&hl=en&gl=us&udm=28",
      "image": "https://encrypted-tbn3.gstatic.com/shopping?q=tbn:ANd9GcRe2muU4URXxsru0Yj8gigEfiATPlsN7zi2ZXa__Wv3Q6-DL-oZJEqRX8HmsD5XQr65BJcXlNcfgOYqk48MeJNesC50lbfhvA",
      "platform": "Google Shopping",
      "source": "Gracious Pharmaceuticals",
      "rating": "",
      "reviews": ""
    },
    {
      "title": "Weighted Linen Blanket: Washable Sensory Comforter, Natural Gravity Blanket, Heavy Blanket For Adults Christmas gift",
      "price": 108.14,
      "currency": "USD",
      "url": "https://www.google.com/search?ibp=oshop&q=Gravity Weighted Blanket&prds=productid:16096223427691498710,headlineOfferDocid:16096223427691498710,imageDocid:17484413894028583199,rds:LO_16096223427691498710|PROD_LO_16096223427691498710,pvt:hg&hl=en&gl=us&udm=28",
      "image": "https://encrypted-tbn3.gstatic.com/shopping?q=tbn:ANd9GcR6K4Xm2d92XNlF6R78SWup_T_NIXtWxfVSBr07XBO9oadSR5gjhwcsxGIqzoqmP089drcf4C1-_5o1J3k1k4GigiKe3PsnTHXI_I69P9si",
      "platform": "Google Shopping",
      "source": "Etsy - LinenHygge",
      "rating": 4.8,
      "reviews": 46
    },
    {
      "title": "Zero Gravity Gravity Grey Weighted Blanket Single 20LB Grey - Home | Color: Grey",
      "price": 100.0,
      "currency": "USD",
      "url": "https://www.google.com/search?ibp=oshop&q=Gravity Weighted Blanket&prds=productid:16398225553380314176,headlineOfferDocid:16398225553380314176,imageDocid:4201551731759598068,pvt:hg&hl=en&gl=us&udm=28",
      "image": "https://encrypted-tbn0.gstatic.com/shopping?q=tbn:ANd9GcTQt2rBmC6QdCrGlSYqVT7eXjJNQZGsDxnJsZ2CZnq2blD5kLJDwgZYFvuLu-TQ1ghlGHGJrh_eAJrjLDtWM34ROX94O6392xEwcX5vvoI",
      "platform": "Google Shopping",
      "source": "Mercari",
      "rating": "",
      "reviews": ""
    },
    {
      "title": "Gravity Blanket Weighted Blanket for Adults, 20lbs Gray 48\"x72\" Twin Single NEW",
      "price": 119.0,
      "currency": "USD",
      "url": "https://www.google.com/search?ibp=oshop&q=Gravity Weighted Blanket&prds=productid:14116680975219328980,headlineOfferDocid:14116680975219328980,imageDocid:10101933796597929412,pvt:hg&hl=en&gl=us&udm=28",
      "image": "https://encrypted-tbn0.gstatic.com/shopping?q=tbn:ANd9GcSDDZ14EdDW0vUHFDnnY_itRW9s8CV4VKHW1yiS1rKqfNVhsH_gR0fgk-J_AfeMA5qErnldGet69_ZI2MsW8Pcuqo0pumSF",
      "platform": "Google Shopping",
      "source": "eBay",
      "rating": "",
      "reviews": ""
    },
    {
      "title": "Nuzzie Knit Weighted Blanket",
      "price": 179.0,
      "currency": "USD",
      "url": "https://www.google.com/search?ibp=oshop&q=Gravity Weighted Blanket&prds=catalogid:7327670496630604548,headlineOfferDocid:17937503522733871872,imageDocid:9484912296734825158,rds:PC_9415545958970846077|PROD_PC_9415545958970846077,gpcid:9415545958970846077,mid:576462597365332049,pvt:hg&hl=en&gl=us&udm=28",
      "image": "https://encrypted-tbn2.gstatic.com/shopping?q=tbn:ANd9GcQXm7Q6-mw8IB-3WHEuVOs4ePoxNG6mmB4nU7RIqNfAjOaTJAqjkv2F6AaZoRWGXe0QJKpF-msQsDCpKju-vKeQvxYIH0yjN7Gj08r1gqEs6VVLr18Bhnx3qw",
      "platform": "Google Shopping",
      "source": "Nuzzie",
      "rating": 4.4,
      "reviews": 906
    },
    {
      "title": "Gravity Blanket - Sensory Calming Weighted Blanket",
      "price": 37.88,
      "currency": "USD",
      "url": "https://www.google.com/search?ibp=oshop&q=Gravity Weighted Blanket&prds=productid:5150185959141642561,headlineOfferDocid:5150185959141642561,imageDocid:6179320666889043734,pvt:hg&hl=en&gl=us&udm=28",
      "image": "https://encrypted-tbn2.gstatic.com/shopping?q=tbn:ANd9GcSWKMiCV43skZ-28k_ya7zbW3GdDXeUDdOyz1vybiNCG_TVX65kNY_nETh_cVj7H1h1GFvJdkDkRrW7N8IjQI6Zoy2D8wGlcl-KLJNM-KDRE8ffJPtgPEOE",
      "platform": "Google Shopping",
      "source": "Alibaba.com",
      "rating": "",
      "reviews": ""
    },
    {
      "title": "Moderne Elegance Gray Polyester Gravity Weighted Blanket 50\" x 60\" | Machine Washable | China | Bedroom | Solid Color | Contemporary | Adults",
      "price": 31.74,
      "currency": "USD",
      "url": "https://www.google.com/search?ibp=oshop&q=Gravity Weighted Blanket&prds=productid:6489464891878620921,headlineOfferDocid:6489464891878620921,imageDocid:4375922618400323036,pvt:hg&hl=en&gl=us&udm=28",
      "image": "https://encrypted-tbn0.gstatic.com/shopping?q=tbn:ANd9GcQJae7orBHXChjziNEAsT1aFsjxOh6nnBSGAJ0gxQ2IM23Eqv73V4MxeYNHRMyJeZS3Yjk_k3lqTRjfWRtYa6y0zWDvQFuzffLq5cZCgFw",
      "platform": "Google Shopping",
      "source": "eBay - vendnthings",
      "rating": "",
      "reviews": ""
    },
    {
      "title": "Zero Gravity Altavida Weighted Blanket 12-lbs - New Home",
      "price": 42.0,
      "currency": "USD",
      "url": "https://www.google.com/search?ibp=oshop&q=Gravity Weighted Blanket&prds=productid:5947132208349158323,headlineOfferDocid:5947132208349158323,imageDocid:9277723584792047994,pvt:hg&hl=en&gl=us&udm=28",
      "image": "https://encrypted-tbn2.gstatic.com/shopping?q=tbn:ANd9GcSMnTByQTaUdMxGkG9-ltKV4OZPj4CxHn_64Vb0D9SSbpcpIWtRq5f8yc7IhrNFePeM8g-GunIRbICHTwwBcOp5_Cv74k8UtuPyA71Ui6gZL1p1o8aqE10p",
      "platform": "Google Shopping",
      "source": "Mercari",
      "rating": "",
      "reviews": ""
    },
    {
      "title": "Weighted Gravity Blanket For Anxiety & Sleep - Glass Bead Filled, OEKO-TEX Certified (Charcoal Grey, Blue)",
      "price": 17.0,
      "currency": "USD",
      "url": "https://www.google.com/search?ibp=oshop&q=Gravity Weighted Blanket&prds=productid:5216923587932495656,headlineOfferDocid:5216923587932495656,imageDocid:483251860817317024,pvt:hg&hl=en&gl=us&udm=28",
      "image": "https://encrypted-tbn0.gstatic.com/shopping?q=tbn:ANd9GcRzq7Fn0tvX0P9aTOEmzVCOPp9cl8gERrAD0kxtYHuEuzWcZRSpDC1wBsAHuN2dmimoEZNOS3W3XA7I0bbMpoasAKr7wo2d",
      "platform": "Google Shopping",
      "source": "Onefulfillment",
      "rating": "",
      "reviews": ""
    },
    {
      "title": "ZENY Twin Quiet Sleep Heavy Weighted Blanket",
      "price": 24.59,
      "currency": "USD",
      "url": "https://www.google.com/search?ibp=oshop&q=Gravity Weighted Blanket&prds=catalogid:17230397198524460017,headlineOfferDocid:8446436028266669616,imageDocid:8260691254019701622,rds:PC_129378287429241938|PROD_PC_129378287429241938,gpcid:129378287429241938,mid:576462859456368267,pvt:hg&hl=en&gl=us&udm=28",
      "image": "https://encrypted-tbn2.gstatic.com/shopping?q=tbn:ANd9GcQkS079OYwtgDhcGPYkbZ3dYMbuY838BSBggzbkoG4RbhNtReDOm1R2nd-Ymdl4VMFmhdTGLvGWo6y00REvSGqrI2oVxkjanESIi3tNFR-UN4npsZCAV85Otg",
      "platform": "Google Shopping",
      "source": "eBay - pro-equipment-supplier",
      "rating": 5.0,
      "reviews": 2
    }
  ]
}